dff_4bitreg.v
module dff(b,clk,q,q_0);
	input b, clk;
	output q,q_0;
	reg q;
	reg q_0;
	
	always@(posedge clk)
	begin
		q <= b;
		q_0 <= !b;
	end
endmodule

module sreg(b,clock,q4,q0_4);
	input b, clock;
	output q4, q0_4;
	//dff ff0, ff1, ff2, ff3;
	//wire w1, w2, w3, w4;
	wire q1, q2, q3;
	wire q_01,q0_2, q0_3;
	//w1 = w2 = w3 = w4 = clock;
	//always@(posedge clock)
	//begin
		dff ff0(.b(b), .clk(clock),.q(q1),.q_0(q0_1));
		dff ff1(.b(q1),.clk(clock),.q(q2),.q_0(q0_2));
		dff ff2(.b(q2),.clk(clock),.q(q3),.q_0(q0_3));
		dff ff3(.b(q3),.clk(clock),.q(q4),.q_0(q0_4));
	//end;
endmodule

dff_tb.v
module dff_tb;

reg clock, reset, d;
wire q, q_0;

initial begin
	$dumpfile("dff_tb.vcd");
	$dumpvars(1,dff_tb);
	$monitor("clk=%b, d=%b,q=%b,q_0=%b", clock, d, q, q_0);
	clock = 0;
	d = 1;
	#10 d = 0;
	#12 d = 1;
	#18 d = 0;
	#20 $finish;
end

always 
	begin #5 clock = !clock;
end

dff d0( .b(d), .clk(clock), .q(q), .q_0(q_0));

endmodule

dff_tb.vcd
$date
	Mon Jan 27 10:47:42 2014
$end
$version
	Icarus Verilog
$end
$timescale
	1s
$end
$scope module dff_tb $end
$var wire 1 ! q $end
$var wire 1 " q_0 $end
$var reg 1 # clock $end
$var reg 1 $ d $end
$upscope $end
$enddefinitions $end
#0
$dumpvars
1$
0#
x"
x!
$end
#5
0"
1!
1#
#10
0#
0$
#15
1"
0!
1#
#20
0#
#22
1$
#25
0"
1!
1#
#30
0#
#35
1#
#40
0#
0$
#45
1"
0!
1#
