regadd_filter.v
//Gate Level Design of FA. LSC2014
module fa(a,b,cin,sum,cout);
        input a,b,cin;
        output sum, cout;

        assign sum = cin ^ a ^ b;
        assign cout = ~cin & a & b| cin & (a|b);
//assigns the carryout and sum bits. Next step is to develop a ripple carry procedure.
endmodule

//Half Adder

module ha(a,b,sum,carry);
        input a,b;
        output sum,carry;

        assign sum = (a&(~b))|((~a)&(b));
        assign carry = a&b;
endmodule

module dff(b,clk,q,q_0);
        input b, clk;
        output q,q_0;
        reg q;
        reg q_0;

        always@(posedge clk)
        begin
                q <= b;
                q_0 <= !b;
        end
endmodule

module sreg(b,clock,q4,q0_4);
        input b, clock;
        output q4, q0_4;
        //dff ff0, ff1, ff2, ff3;
        //wire w1, w2, w3, w4;
        wire q1, q2, q3;
        wire q_01,q0_2, q0_3;
        //w1 = w2 = w3 = w4 = clock;
        //always@(posedge clock)
        //begin
                dff ff0(.b(b), .clk(clock),.q(q1),.q_0(q0_1));
                dff ff1(.b(q1),.clk(clock),.q(q2),.q_0(q0_2));
                dff ff2(.b(q2),.clk(clock),.q(q3),.q_0(q0_3));
                dff ff3(.b(q3),.clk(clock),.q(q4),.q_0(q0_4));
        //end;
endmodule

module fil(in,out,w0,clk);
	input in, clk;
	output out,w0;
	
	wire w1,w2,w3,w4;
	sreg s0(.b(in),.clock(clk),.q4(w0),.q0_4(w1));
	ha h0(.a(in),.b(w0),.sum(out),.carry(w4));
endmodule

regadd_tb.v
module fil_tb;

reg clock, in;
wire out,w0;

initial begin
	$dumpfile("fil_tb.vcd");
	$dumpvars(1,fil_tb);
	clock = 0;
	in=1;
	#10 in = 0;
        #12 in = 1;
        #18 in = 0;
	#20 in= 0;
	#25 in= 1;
	#26 in=0;
	#30 in=1;
	#37 in=0;
        #40 $finish;
end

always
	begin #3 clock = !clock;
end

fil f0(.in(in),.out(out),.w0(w0),.clk(clock));

endmodule

fil_tb.vcd
$date
	Tue Feb 11 14:28:17 2014
$end
$version
	Icarus Verilog
$end
$timescale
	1s
$end
$scope module fil_tb $end
$var wire 1 ! out $end
$var wire 1 " w0 $end
$var reg 1 # clock $end
$var reg 1 $ in $end
$upscope $end
$enddefinitions $end
#0
$dumpvars
1$
0#
x"
x!
$end
#3
1#
#6
0#
#9
1#
#10
0$
#12
0#
#15
1#
#18
0#
#21
1!
1"
1#
#22
0!
1$
#24
0#
#27
1#
#30
0#
#33
1!
0"
1#
#36
0#
#39
1#
#40
0!
0$
#42
0#
#45
1!
1"
1#
#48
0#
#51
1#
#54
0#
#57
1#
#60
0#
#63
0!
0"
1#
#66
0#
#69
1#
#72
0#
#75
1#
#78
0#
#81
1#
#84
0#
#85
1!
1$
#87
1#
#90
0#
#93
1#
#96
0#
#99
1#
#102
0#
#105
0!
1"
1#
#108
0#
#111
1!
1#
0$
#114
0#
#117
1#
#120
0#
#123
1#
#126
0#
#129
0!
0"
1#
#132
0#
#135
1#
#138
0#
#141
1!
1#
1$
#144
0#
#147
1#
#150
0#
#153
1#
#156
0#
#159
0!
1"
1#
#162
0#
#165
1#
#168
0#
#171
1#
#174
0#
#177
1#
#178
1!
0$
#180
0#
#183
1#
#186
0#
#189
1#
#192
0#
#195
1#
#198
0#
#201
0!
0"
1#
