vtest_driver.v
module btoe;
	wire eSeg,p1,p2,p3,p4;
	reg A,B,C,D;
	//initial begin
	//$dumpfile("vtsim.vcd");
	//$dumpvars(0,btoe);	
	nand #1
		g1(p1,C,~D),
		g2 (p2, A, B),
		g3 (p3, ~B, ~D),
		g4 (p4, A, C),
		g5 (eSeg, p1, p2, p3, p4);
//Driver setup
initial
	begin
	$dumpfile("vtsimd1.vcd");
	$dumpvars(0,btoe);
// two slashes introduce a single line comment
	$monitor ($time,,,
		"A = %b B = %b C = %b D = %b, eSeg = %b",
		A,B,C,D, eSeg);
		//waveform for simulating the binaryToESeg driver
		#10 A = 0; B = 0; C = 0; D = 0;
		#10 D = 1;
		#10 C = 1; D = 0;
		#10 $finish;
	end
endmodule
//end driver

vtsimd1.vcd
$date
	Sat Oct 12 08:58:46 2013
$end
$version
	Icarus Verilog
$end
$timescale
	1s
$end
$scope module btoe $end
$var wire 1 ! eSeg $end
$var wire 1 " p1 $end
$var wire 1 # p2 $end
$var wire 1 $ p3 $end
$var wire 1 % p4 $end
$var reg 1 & A $end
$var reg 1 ' B $end
$var reg 1 ( C $end
$var reg 1 ) D $end
$upscope $end
$enddefinitions $end
#0
$dumpvars
x)
x(
x'
x&
x%
x$
x#
x"
z!
$end
#10
0)
0(
0'
0&
#11
0$
1"
1%
1#
#12
1!
#20
1)
#21
1$
#22
0!
#30
0)
1(
#31
0$
0"
#32
1!
